AIOAladdinConnect/__init__.py
AIOAladdinConnect/const.py
AIOAladdinConnect/session_manager.py
AIOAladdinConnect-0.2.0.dist-info/METADATA
AIOAladdinConnect-0.2.0.dist-info/WHEEL
AIOAladdinConnect-0.2.0.dist-info/top_level.txt
AIOAladdinConnect-0.2.0.dist-info/RECORD
