Metadata-Version: 2.1
Name: AIOAladdinConnect
Version: 0.2.0
Summary: Python Async API for controlling Genie garage doors connected to Aladdin Connect devices
Home-page: http://github.com/mkmer/AIOAladdinConnect
Download-URL: https://github.com/mkmer/AIOAladdinConnect/archive/refs/tags/0.2.0.tar.gz
Author: Mike Kasper
Author-email: m_kasper@sbcglobal.net
License: MIT
Classifier: Development Status :: 4 - Beta
Classifier: Intended Audience :: Developers
Classifier: License :: OSI Approved :: MIT License
Classifier: Operating System :: OS Independent
Classifier: Programming Language :: Python
Requires-Dist: aiohttp
Requires-Dist: aioboto3
